platform_api/__init__.py
platform_api/adapters/AssetGroupAssetsAPIClient.py
platform_api/adapters/AssetGroupsAPIClient.py
platform_api/adapters/AssetTagsAPIClient.py
platform_api/adapters/AssetsAPIClient.py
platform_api/adapters/BaseAPIClient.py
platform_api/adapters/CompaniesAPIClient.py
platform_api/adapters/IssueCommentsAPIClient.py
platform_api/adapters/IssuesAPIClient.py
platform_api/adapters/MergeSettingsAPIClient.py
platform_api/adapters/PhaseHostIssuesAPIClient.py
platform_api/adapters/PhaseHostsAPIClient.py
platform_api/adapters/PhaseIssuesAPIClient.py
platform_api/adapters/PhaseReviewersAPIClient.py
platform_api/adapters/PhaseTagsAPIClient.py
platform_api/adapters/PhaseTestersAPIClient.py
platform_api/adapters/PhasesAPIClient.py
platform_api/adapters/ProjectCommentsAPIClient.py
platform_api/adapters/ProjectTagsAPIClient.py
platform_api/adapters/ProjectsAPIClient.py
platform_api/adapters/TagsAPIClient.py
platform_api/adapters/TestTypesAPIClient.py
platform_api/adapters/UsersAPIClient.py
platform_api/adapters/__init__.py
platform_api/cli.py
platform_api/cli_commands/__init__.py
platform_api/cli_commands/phases/create.py
platform_api/cli_commands/project_remediation_types/get_remediation_types.py
platform_api/cli_commands/project_service_types/get_service_types.py
platform_api/cli_commands/project_statuses/get_statuses.py
platform_api/cli_commands/project_tags/delete.py
platform_api/cli_commands/project_tags/get_paginated.py
platform_api/cli_commands/project_tags/update.py
platform_api/cli_commands/project_tags/update_from_list.py
platform_api/cli_commands/projects/__init__.py
platform_api/cli_commands/projects/create.py
platform_api/cli_commands/projects/delete.py
platform_api/cli_commands/projects/export_to_csv.py
platform_api/cli_commands/projects/get_paginated.py
platform_api/cli_commands/projects/get_single.py
platform_api/cli_commands/projects/update.py
platform_api/cli_commands/tags/__init__.py
platform_api/cli_commands/tags/create.py
platform_api-0.1.1.dist-info/METADATA
platform_api-0.1.1.dist-info/WHEEL
platform_api-0.1.1.dist-info/entry_points.txt
platform_api-0.1.1.dist-info/RECORD
