Metadata-Version: 2.1
Name: platform_api
Version: 0.1.1
Summary: A Package to interact with Rootshells Public API
Author: Chris
Author-email: chris.mills@rootshellsecurity.net
Requires-Python: >=3.10,<4.0
Classifier: Programming Language :: Python :: 3
Classifier: Programming Language :: Python :: 3.10
Classifier: Programming Language :: Python :: 3.11
Classifier: Programming Language :: Python :: 3.12
Requires-Dist: click (>=8.1.7,<9.0.0)
Requires-Dist: pandas (>=2.2.2,<3.0.0)
Requires-Dist: python-dotenv (>=1.0.1,<2.0.0)
Requires-Dist: requests (>=2.32.3,<3.0.0)
